odoo8_addon_l10n_it_withholding_tax_causali-8.0.2.0.0-nspkg.pth
odoo_addons/l10n_it_withholding_tax_causali/README.rst
odoo_addons/l10n_it_withholding_tax_causali/__init__.py
odoo_addons/l10n_it_withholding_tax_causali/__openerp__.py
odoo_addons/l10n_it_withholding_tax_causali/i18n/it.po
odoo_addons/l10n_it_withholding_tax_causali/i18n/l10n_it_withholding_tax_causali.pot
odoo_addons/l10n_it_withholding_tax_causali/models/__init__.py
odoo_addons/l10n_it_withholding_tax_causali/models/withholding_tax.py
odoo_addons/l10n_it_withholding_tax_causali/readme/DESCRIPTION.rst
odoo_addons/l10n_it_withholding_tax_causali/static/description/icon.png
odoo_addons/l10n_it_withholding_tax_causali/static/description/index.html
odoo_addons/l10n_it_withholding_tax_causali/views/withholding_tax.xml
odoo8_addon_l10n_it_withholding_tax_causali-8.0.2.0.0.dist-info/METADATA
odoo8_addon_l10n_it_withholding_tax_causali-8.0.2.0.0.dist-info/WHEEL
odoo8_addon_l10n_it_withholding_tax_causali-8.0.2.0.0.dist-info/namespace_packages.txt
odoo8_addon_l10n_it_withholding_tax_causali-8.0.2.0.0.dist-info/top_level.txt
odoo8_addon_l10n_it_withholding_tax_causali-8.0.2.0.0.dist-info/RECORD
