Metadata-Version: 2.1
Name: odoo8-addon-l10n-it-withholding-tax-causali
Version: 8.0.2.0.0
Summary: Causali pagamento per ritenute d'acconto
Home-page: https://github.com/OCA/l10n-italy
Author: Agile Business Group, Odoo Community Association (OCA)
Author-email: support@odoo-community.org
License: LGPL-3
Platform: UNKNOWN
Classifier: Programming Language :: Python
Classifier: Framework :: Odoo
Classifier: License :: OSI Approved :: GNU Lesser General Public License v3 (LGPLv3)
Classifier: Development Status :: 4 - Beta
Requires-Python: ~=2.7
Requires-Dist: odoo8-addon-l10n-it-causali-pagamento
Requires-Dist: odoo8-addon-l10n-it-withholding-tax
Requires-Dist: odoo (<9.0a,>=8.0a)
